positiontools/__init__.py
positiontools/positionutil.py
python_positiontools-1.0.1.dist-info/LICENSE
python_positiontools-1.0.1.dist-info/METADATA
python_positiontools-1.0.1.dist-info/WHEEL
python_positiontools-1.0.1.dist-info/top_level.txt
python_positiontools-1.0.1.dist-info/RECORD
